flask_shell.py
flask_shell-0.1.8.dist-info/METADATA
flask_shell-0.1.8.dist-info/WHEEL
flask_shell-0.1.8.dist-info/entry_points.txt
flask_shell-0.1.8.dist-info/top_level.txt
flask_shell-0.1.8.dist-info/RECORD
